dpsa4flower/__init__.py
dpsa4flower/dpsa_numpy_client.py
dpsa4flower/dpsa_server.py
dpsa4flower/reshaping_config.py
dpsa4flower-0.6.1.dist-info/WHEEL
dpsa4flower-0.6.1.dist-info/METADATA
dpsa4flower-0.6.1.dist-info/RECORD
