Metadata-Version: 2.1
Name: dpsa4flower
Version: 0.6.1
Summary: A server and client to use the flower framework with DPSA.
Author: Maxim Urschumzew
Author-email: maxim@makuri.dev
Requires-Python: >=3.8,<4.0
Classifier: Programming Language :: Python :: 3
Classifier: Programming Language :: Python :: 3.8
Classifier: Programming Language :: Python :: 3.9
Classifier: Programming Language :: Python :: 3.10
Classifier: Programming Language :: Python :: 3.11
Requires-Dist: dataclass-wizard (>=0.22.2,<0.23.0)
Requires-Dist: dpsa4fl-bindings (>=0.1.3,<0.2.0)
Requires-Dist: flwr (>=1.4.0,<2.0.0)
Requires-Dist: numpy (>=1.24.3,<2.0.0)
